[
     {
          "id": 4,
          "title": "Practical Concrete Pants",
          "description": "9",
          "code": "TCP",
          "price": 38.09,
          "status": true,
          "stock": 63,
          "category": "Acessorios",
          "thumbnail": []
     },
     {
          "id": 5,
          "title": "Fantastic Wooden Keyboard",
          "description": "l",
          "code": "EXE",
          "price": 52.53,
          "status": true,
          "stock": 63,
          "category": "Acessorios",
          "thumbnail": []
     },
     {
          "id": 6,
          "title": "Handmade Plastic Keyboard",
          "description": "x",
          "code": "XML",
          "price": 407.21,
          "status": true,
          "stock": 63,
          "category": "Acessorios",
          "thumbnail": []
     },
     {
          "id": 7,
          "title": "Rustic Concrete Bacon",
          "description": "e",
          "code": "AGP",
          "price": 927.9,
          "status": true,
          "stock": 63,
          "category": "Acessorios",
          "thumbnail": []
     },
     {
          "id": 9,
          "title": "Practical Granite Tuna",
          "description": "i",
          "code": "e3dd",
          "price": 175.41,
          "status": true,
          "stock": 50,
          "category": "Varios",
          "thumbnail": []
     },
     {
          "id": 10,
          "title": "Refined Plastic Chair",
          "description": "r",
          "code": "2woj",
          "price": 558.99,
          "status": true,
          "stock": 50,
          "category": "Varios",
          "thumbnail": []
     },
     {
          "id": 11,
          "title": "Awesome Plastic Mouse",
          "description": "c",
          "code": "9zmq",
          "price": 713.4,
          "status": true,
          "stock": 50,
          "category": "Varios",
          "thumbnail": []
     },
     {
          "id": 12,
          "title": "Handcrafted Soft Computer",
          "description": "4",
          "code": "16ff",
          "price": 493.19,
          "status": true,
          "stock": 50,
          "category": "Varios",
          "thumbnail": []
     },
     {
          "id": 13,
          "title": "Licensed Cotton Car",
          "description": "d",
          "code": "lg85",
          "price": 190.35,
          "status": true,
          "stock": 50,
          "category": "Varios",
          "thumbnail": []
     },
     {
          "id": 14,
          "title": "Rustic Fresh Keyboard",
          "description": "c",
          "code": "t9cu",
          "price": 453.67,
          "status": true,
          "stock": 50,
          "category": "Varios",
          "thumbnail": []
     },
     {
          "id": 15,
          "title": "Handmade Wooden Computer",
          "description": "e",
          "code": "lf8n",
          "price": 172.08,
          "status": true,
          "stock": 50,
          "category": "Varios",
          "thumbnail": []
     },
     {
          "id": 16,
          "title": "Gorgeous Fresh Pants",
          "description": "2",
          "code": "y9uj",
          "price": 984.08,
          "status": true,
          "stock": 50,
          "category": "Varios",
          "thumbnail": []
     },
     {
          "id": 17,
          "title": "Rustic Steel Soap",
          "description": "x",
          "code": "kuni",
          "price": 382.15,
          "status": true,
          "stock": 50,
          "category": "Varios",
          "thumbnail": []
     },
     {
          "id": 19,
          "title": "Handcrafted Metal Towels",
          "description": "1",
          "code": "kuob",
          "price": 650.97,
          "status": true,
          "stock": 50,
          "category": "Varios",
          "thumbnail": []
     },
     {
          "id": 20,
          "title": "Incredible Granite Car",
          "description": "b",
          "code": "1dzl",
          "price": 837.42,
          "status": true,
          "stock": 50,
          "category": "Varios",
          "thumbnail": []
     },
     {
          "id": 21,
          "title": "Awesome Metal Table",
          "description": "i",
          "code": "3liz",
          "price": 936.35,
          "status": true,
          "stock": 50,
          "category": "Varios",
          "thumbnail": []
     },
     {
          "id": 22,
          "title": "Generic Soft Pants",
          "description": "x",
          "code": "xsb8",
          "price": 792.18,
          "status": true,
          "stock": 50,
          "category": "Varios",
          "thumbnail": []
     },
     {
          "id": 23,
          "title": "Refined Frozen Shirt",
          "description": "1",
          "code": "f68q",
          "price": 640.43,
          "status": true,
          "stock": 50,
          "category": "Varios",
          "thumbnail": []
     },
     {
          "id": 25,
          "title": "Unbranded Metal Gloves",
          "description": "p",
          "code": "7cl4",
          "price": 294.69,
          "status": true,
          "stock": 50,
          "category": "Varios",
          "thumbnail": []
     },
     {
          "id": 26,
          "title": "Small Wooden Keyboard",
          "description": "p",
          "code": "paq7",
          "price": 306.43,
          "status": true,
          "stock": 50,
          "category": "Varios",
          "thumbnail": []
     },
     {
          "id": 27,
          "title": "Incredible Rubber Gloves",
          "description": "z",
          "code": "v6q5",
          "price": 444.55,
          "status": true,
          "stock": 50,
          "category": "Varios",
          "thumbnail": []
     }
]